README.md
setup.cfg
setup.py
clubhouse_api/__init__.py
clubhouse_api/clubhouse.py
clubhouse_api/enums.py
clubhouse_api/exceptions.py
clubhouse_api/utils.py
clubhouse_api.egg-info/PKG-INFO
clubhouse_api.egg-info/SOURCES.txt
clubhouse_api.egg-info/dependency_links.txt
clubhouse_api.egg-info/requires.txt
clubhouse_api.egg-info/top_level.txt