Metadata-Version: 2.1
Name: clubhouse-api
Version: 1.0.2
Summary: Python module for writing scripts for project management platform Club House (clubhouse.io API wrapper)
Home-page: https://github.com/Peopl3s/club-house-api
Author: Peopl3s
Author-email: peoplesdreamer@gmail.ru
License: Apache License, Version 2.0, see LICENSE file
Download-URL: https://github.com/Peopl3s/club-house-api/archive/main.zip
Platform: UNKNOWN
Classifier: License :: OSI Approved :: Apache Software License
Classifier: Operating System :: OS Independent
Classifier: Intended Audience :: End Users/Desktop
Classifier: Intended Audience :: Developers
Classifier: Programming Language :: Python
Classifier: Programming Language :: Python :: 3
Classifier: Programming Language :: Python :: 3.6
Classifier: Programming Language :: Python :: 3.7
Classifier: Programming Language :: Python :: 3.8
Classifier: Programming Language :: Python :: Implementation :: PyPy
Classifier: Programming Language :: Python :: Implementation :: CPython
